vulfocus_client_api/__init__.py
vulfocus_client_api/hostEntity.py
vulfocus_client_api/imageEntity.py
vulfocus_client_api/operationConstants.py
vulfocus_client_api/vulfocusClient.py
vulfocus_client_api/vulfocusException.py
vulfocustest3-0.0.1.dist-info/LICENSE
vulfocustest3-0.0.1.dist-info/METADATA
vulfocustest3-0.0.1.dist-info/WHEEL
vulfocustest3-0.0.1.dist-info/top_level.txt
vulfocustest3-0.0.1.dist-info/RECORD
